shadowpxmeter/__init__.py
shadowpxmeter/calc_metric.py
shadowpxmeter/cli.py
shadowpxmeter/constants.py
shadowpxmeter/eval.py
shadowpxmeter/mapping.py
shadowpxmeter/utils.py
shadowpxmeter/configs/__init__.py
shadowpxmeter/configs/data_config.py
shadowpxmeter/configs/run_config.py
shadowpxmeter/data/__init__.py
shadowpxmeter/data/ccd.py
shadowpxmeter/data/parser.py
shadowpxmeter/data/struct.py
shadowpxmeter/data/utils.py
shadowpxmeter/data/writer.py
shadowpxmeter/metrics/__init__.py
shadowpxmeter/metrics/clashes.py
shadowpxmeter/metrics/lddt_metrics.py
shadowpxmeter/metrics/rmsd.py
shadowpxmeter/metrics/rmsd_metrics.py
shadowpxmeter/permutation/__init__.py
shadowpxmeter/permutation/atom.py
shadowpxmeter/permutation/chain.py
shadowpxmeter-0.0.3.dist-info/licenses/LICENSE
shadowpxmeter-0.0.3.dist-info/METADATA
shadowpxmeter-0.0.3.dist-info/WHEEL
shadowpxmeter-0.0.3.dist-info/entry_points.txt
shadowpxmeter-0.0.3.dist-info/top_level.txt
shadowpxmeter-0.0.3.dist-info/RECORD
